simple_icd_11/__init__.py
simple_icd_11/simple_icd_11.py
simple_icd_11-1.2.0.dist-info/licenses/LICENSE
simple_icd_11-1.2.0.dist-info/METADATA
simple_icd_11-1.2.0.dist-info/WHEEL
simple_icd_11-1.2.0.dist-info/top_level.txt
simple_icd_11-1.2.0.dist-info/RECORD
