Metadata-Version: 2.4
Name: simple_icd_11
Version: 1.2.0
Summary: A simple python library for ICD-11 MMS codes
Author-email: Stefano Travasci <stefanotravasci@gmail.com>
Project-URL: Homepage, https://simpleicd11.stefanotravasci.it
Project-URL: repository, https://github.com/StefanoTrv/simple_icd_11
Project-URL: documentation, https://simpleicd11.stefanotravasci.it
Project-URL: Issues, https://github.com/StefanoTrv/simple_icd_11/issues
Project-URL: forum, https://github.com/StefanoTrv/simple_icd_11/discussions
Project-URL: donate, https://github.com/StefanoTrv/simple_icd_11?tab=readme-ov-file#conclusion
Keywords: icd,icd 11,icd-11,icd-11-MMS,icd-11 MMS,icd 11 MMS,icd11,Mortality and Morbidity Statistics,Health informatics,International Classification of Diseases
Classifier: Programming Language :: Python :: 3
Classifier: License :: OSI Approved :: MIT License
Classifier: Operating System :: OS Independent
Requires-Python: >=3.8
License-File: LICENSE
Requires-Dist: requests
Dynamic: license-file
